README.md
setup.py
buzzer/__init__.py
micropython_buzzer.egg-info/PKG-INFO
micropython_buzzer.egg-info/SOURCES.txt
micropython_buzzer.egg-info/dependency_links.txt
micropython_buzzer.egg-info/top_level.txt
test/test_buzzer.py
test/test_midi.py